hug_peewee_connect
tests
