Metadata-Version: 1.1
Name: hug-peewee-connect
Version: 0.0.2
Summary: Simple and clean integration with the peewee ORM
Home-page: https://github.com/soloman1124/hug_peewee_connect
Author: Soloman Weng
Author-email: soloman1124@gmail.com
License: UNKNOWN
Platform: UNKNOWN
Classifier: Development Status :: 2 - Pre-Alpha
Classifier: Programming Language :: Python
Classifier: Programming Language :: Python :: 2
Classifier: Programming Language :: Python :: 2.7
Classifier: Programming Language :: Python :: 3
Classifier: Programming Language :: Python :: 3.4
Classifier: Programming Language :: Python :: 3.5
